llama_index/multi_modal_llms/nvidia/__init__.py
llama_index/multi_modal_llms/nvidia/base.py
llama_index/multi_modal_llms/nvidia/utils.py
llama_index_multi_modal_llms_nvidia-0.5.2.dist-info/METADATA
llama_index_multi_modal_llms_nvidia-0.5.2.dist-info/WHEEL
llama_index_multi_modal_llms_nvidia-0.5.2.dist-info/licenses/LICENSE
llama_index_multi_modal_llms_nvidia-0.5.2.dist-info/RECORD
