Metadata-Version: 2.4
Name: llama-index-multi-modal-llms-nvidia
Version: 0.5.2
Summary: llama-index multi_modal nvidia integration
Author-email: Your Name <you@example.com>
License-Expression: MIT
License-File: LICENSE
Requires-Python: <4.0,>=3.9
Requires-Dist: filetype<2,>=1.2.0
Requires-Dist: llama-index-core<0.15,>=0.13.0
Requires-Dist: llama-index-llms-nvidia<1,>=0.3.4
